octofludb/__init__.py
octofludb/classes.py
octofludb/classifier_flucrew.py
octofludb/cli.py
octofludb/colors.py
octofludb/domain_animal.py
octofludb/domain_date.py
octofludb/domain_flu.py
octofludb/domain_geography.py
octofludb/domain_identifier.py
octofludb/domain_sequence.py
octofludb/entrez.py
octofludb/formatting.py
octofludb/genbank.py
octofludb/graph.py
octofludb/hash.py
octofludb/nomenclature.py
octofludb/parser.py
octofludb/py.typed
octofludb/recipes.py
octofludb/script.py
octofludb/spellcheck.py
octofludb/token.py
octofludb/ui.py
octofludb/util.py
octofludb/version.py
octofludb/data/all-acc.rq
octofludb/data/clear-query-tags.rq
octofludb/data/config.yaml
octofludb/data/delete-constellations.rq
octofludb/data/delete-gl_clades.rq
octofludb/data/delete-motifs.rq
octofludb/data/delete-subtypes.rq
octofludb/data/delete-us_clades.rq
octofludb/data/fetch-unclassified-swine.rq
octofludb/data/geography.ttl
octofludb/data/get-h1-sequences.rq
octofludb/data/get-h1-swine.rq
octofludb/data/get-h3-sequences.rq
octofludb/data/get-h3-swine.rq
octofludb/data/get-tagged-isolate.rq
octofludb/data/get-tagged-segment.rq
octofludb/data/get-tagged-sequence.rq
octofludb/data/get-tagged-strain.rq
octofludb/data/get-tagged.rq
octofludb/data/masterlist.rq
octofludb/data/monthly-context.rq
octofludb/data/octofludb-config.ttl
octofludb/data/schema.ttl
octofludb/data/segments.rq
octofludb/data/subtypes.rq
octofludb/data/wgs.rq
octofludb-1.0.1.dist-info/METADATA
octofludb-1.0.1.dist-info/WHEEL
octofludb-1.0.1.dist-info/entry_points.txt
octofludb-1.0.1.dist-info/top_level.txt
octofludb-1.0.1.dist-info/RECORD
