Metadata-Version: 2.1
Name: octofludb
Version: 1.0.1
Summary: Mangage the flu-crew swine surveillance database
Home-page: https://github.com/flu-crew/octofludb
Author: Zebulun Arendsee
Author-email: zebulun.arendsee@usda.gov
License: UNKNOWN
Platform: UNKNOWN
Classifier: Programming Language :: Python :: 3
Classifier: License :: OSI Approved :: MIT License
Classifier: Operating System :: OS Independent
Requires-Dist: pgraphdb
Requires-Dist: parsec
Requires-Dist: rdflib
Requires-Dist: pandas
Requires-Dist: biopython
Requires-Dist: tqdm
Requires-Dist: xlrd
Requires-Dist: termcolor
Requires-Dist: requests
Requires-Dist: click
Requires-Dist: pyyaml
Requires-Dist: smof
Requires-Dist: flutile
